devito_examples-1.0.dist-info/licenses/LICENSE
seismic/__init__.py
seismic/model.py
seismic/plotting.py
seismic/preset_models.py
seismic/source.py
seismic/utils.py
seismic/acoustic/__init__.py
seismic/acoustic/accuracy.ipynb
seismic/acoustic/acoustic_example.py
seismic/acoustic/operators.py
seismic/acoustic/wavesolver.py
seismic/elastic/__init__.py
seismic/elastic/elastic_example.py
seismic/elastic/operators.py
seismic/elastic/wavesolver.py
seismic/tti/__init__.py
seismic/tti/operators.py
seismic/tti/rotated_fd.py
seismic/tti/tti_example.py
seismic/tti/wavesolver.py
seismic/tutorials/01_modelling.ipynb
seismic/tutorials/02_rtm.ipynb
seismic/tutorials/03_fwi.ipynb
seismic/tutorials/04_dask.ipynb
seismic/tutorials/05_staggered_acoustic.ipynb
seismic/tutorials/06_elastic.ipynb
seismic/tutorials/06_elastic_varying_parameters.ipynb
seismic/tutorials/TLE_Adjoint.ipynb
seismic/tutorials/TLE_Forward.ipynb
seismic/tutorials/TLE_fwi.ipynb
seismic/viscoelastic/__init__.py
seismic/viscoelastic/operators.py
seismic/viscoelastic/viscoelastic_example.py
seismic/viscoelastic/wavesolver.py
devito_examples-1.0.dist-info/METADATA
devito_examples-1.0.dist-info/WHEEL
devito_examples-1.0.dist-info/top_level.txt
devito_examples-1.0.dist-info/RECORD
