Metadata-Version: 2.4
Name: Devito-Examples
Version: 1.0
Summary: Seismic modeling and inversion examples using Devito.
Home-page: https://github.com/slimgroup/Devito-Examples
Author: Georgia Institute of Technology, SLIM Group
Author-email: mlouboutin3@gatech.edu
License: MIT
Project-URL: Documentation, https://slimgroup.github.io/Devito-Examples/
Project-URL: Source, https://github.com/slimgroup/Devito-Examples
Classifier: Programming Language :: Python :: 3
Classifier: License :: OSI Approved :: MIT License
Classifier: Operating System :: OS Independent
Classifier: Intended Audience :: Science/Research
Classifier: Topic :: Scientific/Engineering
Requires-Python: >=3.8
License-File: LICENSE
Requires-Dist: devito[extras,tests]
Dynamic: author
Dynamic: author-email
Dynamic: classifier
Dynamic: description
Dynamic: description-content-type
Dynamic: home-page
Dynamic: license
Dynamic: license-file
Dynamic: project-url
Dynamic: requires-dist
Dynamic: requires-python
Dynamic: summary
